git_remote_dropbox/__init__.py
git_remote_dropbox/constants.py
git_remote_dropbox/git.py
git_remote_dropbox/helper.py
git_remote_dropbox/util.py
git_remote_dropbox/cli/__init__.py
git_remote_dropbox/cli/common.py
git_remote_dropbox/cli/helper.py
git_remote_dropbox/cli/manage.py
git_remote_dropbox-2.0.4.dist-info/METADATA
git_remote_dropbox-2.0.4.dist-info/WHEEL
git_remote_dropbox-2.0.4.dist-info/entry_points.txt
git_remote_dropbox-2.0.4.dist-info/licenses/LICENSE.md
git_remote_dropbox-2.0.4.dist-info/RECORD
