Metadata-Version: 2.4
Name: git-remote-dropbox
Version: 2.0.4
Summary: A transparent bidirectional bridge between Git and Dropbox
Project-URL: homepage, https://github.com/anishathalye/git-remote-dropbox
Project-URL: repository, https://github.com/anishathalye/git-remote-dropbox.git
Project-URL: issues, https://github.com/anishathalye/git-remote-dropbox/issues
Author-email: Anish Athalye <me@anishathalye.com>
License-File: LICENSE.md
Keywords: dropbox,git
Classifier: Development Status :: 5 - Production/Stable
Classifier: Intended Audience :: Developers
Classifier: License :: OSI Approved :: MIT License
Classifier: Programming Language :: Python :: 3
Classifier: Topic :: Software Development :: Version Control
Requires-Python: >=3.6
Requires-Dist: dropbox<13,>=12
